CHANGES.txt
README.txt
bootstrap.py
buildout.cfg
setup.py
src/collective/__init__.py
src/collective.recipe.hudson.egg-info/PKG-INFO
src/collective.recipe.hudson.egg-info/SOURCES.txt
src/collective.recipe.hudson.egg-info/dependency_links.txt
src/collective.recipe.hudson.egg-info/entry_points.txt
src/collective.recipe.hudson.egg-info/namespace_packages.txt
src/collective.recipe.hudson.egg-info/not-zip-safe
src/collective.recipe.hudson.egg-info/requires.txt
src/collective.recipe.hudson.egg-info/top_level.txt
src/collective/recipe/__init__.py
src/collective/recipe/hudson/__init__.py
src/collective/recipe/hudson/templates/hudson.tmpl
src/collective/recipe/hudson/templates/jetty.xml.tmpl