Metadata-Version: 1.0
Name: collective.recipe.hudson
Version: 1.0a3
Summary: Buildout recipe for installing a Hudson instance
Home-page: http://pypi.python.org/pypi/collective.recipe.hudson
Author: Hanno Schlichting
Author-email: hannosch@plone.org
License: ZPL 2.1
Keywords: hudson buildout
Platform: UNKNOWN
Classifier: License :: OSI Approved :: Zope Public License
Classifier: Framework :: Buildout
